LICENCE
MANIFEST.in
README.md
setup.py
allianceauth_tax_tools.egg-info/PKG-INFO
allianceauth_tax_tools.egg-info/SOURCES.txt
allianceauth_tax_tools.egg-info/dependency_links.txt
allianceauth_tax_tools.egg-info/requires.txt
allianceauth_tax_tools.egg-info/top_level.txt
taxtools/__init__.py
taxtools/admin.py
taxtools/api.py
taxtools/apps.py
taxtools/auth_hooks.py
taxtools/models.py
taxtools/tasks.py
taxtools/tax_cog.py
taxtools/urls.py
taxtools/views.py
taxtools/management/commands/__init.py
taxtools/management/commands/tax_defaults.py
taxtools/management/commands/tax_explain.py
taxtools/migrations/0001_initial.py
taxtools/migrations/0002_alter_corppayouttaxconfiguration_corporation_and_more.py
taxtools/migrations/0003_corppayouttaxconfiguration_tax.py
taxtools/migrations/0004_corptaxhistory.py
taxtools/migrations/0005_rename_entry_corptaxhistory_corp.py
taxtools/migrations/0006_alter_corptaxhistory_unique_together.py
taxtools/migrations/0007_rename_corppayouttaxconfiguration_characterpayouttaxconfiguration_and_more.py
taxtools/migrations/0008_rename_corppayouttaxhistory_characterpayouttaxhistory_and_more.py
taxtools/migrations/0009_alter_characterpayouttaxrecord_entry_and_more.py
taxtools/migrations/0010_corptaxpermembertaxconfiguration.py
taxtools/migrations/0011_corptaxperservicemoduleconfiguration.py
taxtools/migrations/0012_corptaxconfiguration_corptaxrecord_and_more.py
taxtools/migrations/0013_alter_corptaxconfiguration_charactertaxesincluded_and_more.py
taxtools/migrations/0014_remove_corptaxperservicemoduleconfiguration_region_filter_and_more.py
taxtools/migrations/0015_corptaxconfiguration_exemptedcorps.py
taxtools/migrations/0016_rename_charactertaxesincluded_corptaxconfiguration_character_taxes_included_and_more.py
taxtools/migrations/0017_corptaxrecord_end_date_corptaxrecord_start_date.py
taxtools/migrations/0018_rename_name_corptaxrecord_name.py
taxtools/migrations/0019_characterpayouttaxrecord_record_and_more.py
taxtools/migrations/0020_alter_characterpayouttaxconfiguration_options_and_more.py
taxtools/migrations/0021_corptaxconfiguration_character_ratting_included.py
taxtools/migrations/0022_corptaxconfiguration_included_alliances.py
taxtools/migrations/__init__.py
